cryptopy/cryptopy.py
cryptopy_cli-1.0.0.dist-info/LICENSE
cryptopy_cli-1.0.0.dist-info/METADATA
cryptopy_cli-1.0.0.dist-info/WHEEL
cryptopy_cli-1.0.0.dist-info/entry_points.txt
cryptopy_cli-1.0.0.dist-info/top_level.txt
cryptopy_cli-1.0.0.dist-info/RECORD
