Metadata-Version: 2.1
Name: cryptopy-cli
Version: 1.0.0
Summary: A CLI based encryption-decryption tool using SHA256
Home-page: https://github.com/MYavuzYAGIS/cryptopy
Author: M.Yavuz Yagis
Author-email: mehmetyavuzyagis@gmail.com
License: MIT
Platform: UNKNOWN
Classifier: Programming Language :: Python :: 3
Classifier: License :: OSI Approved :: MIT License
Classifier: Operating System :: OS Independent
Requires-Dist: click
Requires-Dist: pyfiglet
Requires-Dist: termcolor
Requires-Dist: pycryptodome
